mcrt/__init__.py
mcrt-0.0.0.dist-info/METADATA
mcrt-0.0.0.dist-info/WHEEL
mcrt-0.0.0.dist-info/RECORD
