Metadata-Version: 2.1
Name: mcrt
Version: 0.0.0
Summary: Monte-Carlo Radiative Transfer
Author: FreddyWordingham
Author-email: freddy@digilab.co.uk
Requires-Python: >=3.8,<4.0
Classifier: Programming Language :: Python :: 3
Classifier: Programming Language :: Python :: 3.8
Classifier: Programming Language :: Python :: 3.9
Classifier: Programming Language :: Python :: 3.10
Classifier: Programming Language :: Python :: 3.11
